flexiv_consul_service/__init__.py
flexiv_consul_service/conf/__init__.py
flexiv_consul_service/conf/settings.py
flexiv_consul_service/src/__init__.py
flexiv_consul_service/src/base_service.py
flexiv_consul_service/src/client.py
flexiv_consul_service/test/__init__.py
flexiv_consul_service/test/tests.py
flexiv_consul_service-1.6.dist-info/METADATA
flexiv_consul_service-1.6.dist-info/WHEEL
flexiv_consul_service-1.6.dist-info/top_level.txt
flexiv_consul_service-1.6.dist-info/RECORD
